perprof/__init__.py
perprof/bokeh.py
perprof/main.py
perprof/matplotlib.py
perprof/parse.py
perprof/prof.py
perprof/profile_data.py
perprof/solver_data.py
perprof/tikz.py
perprof/examples/alpha.table
perprof/examples/beta.table
perprof/examples/gamma.table
perprof/locale/en/LC_MESSAGES/perprof.mo
perprof/locale/pt/LC_MESSAGES/perprof.mo
perprof_py-1.1.4.dist-info/AUTHORS
perprof_py-1.1.4.dist-info/LICENSE
perprof_py-1.1.4.dist-info/METADATA
perprof_py-1.1.4.dist-info/WHEEL
perprof_py-1.1.4.dist-info/entry_points.txt
perprof_py-1.1.4.dist-info/top_level.txt
perprof_py-1.1.4.dist-info/RECORD
