Metadata-Version: 2.1
Name: perprof-py
Version: 1.1.4
Summary: A python module for performance profiling (as described by Dolan and Moré)
Author-email: Abel Soares Siqueira <abel.s.siqueira@gmail.com>, Raniere Gaia Costa da Silva <raniere@ime.unicamp.br>, Luiz Rafael dos Santos <l.r.santos@ufsc.br>
License: GNU GENERAL PUBLIC LICENSE
Project-URL: repository, https://github.com/abelsiqueira/perprof-py
Project-URL: documentation, https://perprof-py.readthedocs.org/en/latest/
Keywords: benchmark,comparison,performance profile
Classifier: Programming Language :: Python
Requires-Python: >=3.7
License-File: LICENSE
License-File: AUTHORS
Requires-Dist: pyyaml (<7,>=5)
Requires-Dist: matplotlib (<4,>=3)
Requires-Dist: bokeh (<3,>=2)
Requires-Dist: pandas (<2,>=1)
Provides-Extra: dev
Requires-Dist: black ; extra == 'dev'
Requires-Dist: pre-commit ; extra == 'dev'
Requires-Dist: prospector[with_pyroma] ; extra == 'dev'
Requires-Dist: pylint ; extra == 'dev'
Requires-Dist: pytest ; extra == 'dev'
Requires-Dist: pytest-cov ; extra == 'dev'
Provides-Extra: docs
Requires-Dist: mkdocs ; extra == 'docs'
Requires-Dist: mkdocstrings[python] ; extra == 'docs'
Requires-Dist: mkdocs-material ; extra == 'docs'
Requires-Dist: mike ; extra == 'docs'
Provides-Extra: publishing
Requires-Dist: build ; extra == 'publishing'
Requires-Dist: twine ; extra == 'publishing'
